{"stats":{"minecraft:crafted":{"minecraft:black_dye":12701,"minecraft:chainmail_helmet":22,"minecraft:end_stone_brick_wall":6,"minecraft:melon":1090,"minecraft:birch_boat":1,"minecraft:blaze_powder":78,"minecraft:diorite_stairs":1748,"minecraft:diamond_shovel":20,"minecraft:shulker_box":453,"minecraft:diamond_helmet":9,"minecraft:white_glazed_terracotta":48,"minecraft:stone_pressure_plate":1443,"minecraft:pink_stained_glass":122200,"minecraft:polished_andesite_stairs":640,"minecraft:acacia_slab":5921,"minecraft:sticky_piston":46,"minecraft:stone_brick_stairs":1352,"minecraft:golden_leggings":2,"minecraft:stone_slab":3454,"minecraft:iron_pickaxe":1,"minecraft:netherite_ingot":47,"minecraft:composter":649,"minecraft:dark_prismarine":2504,"minecraft:iron_nugget":1586,"minecraft:diamond_hoe":17,"minecraft:acacia_fence_gate":241,"minecraft:jack_o_lantern":95,"minecraft:prismarine_brick_stairs":100,"minecraft:spruce_fence":1690,"minecraft:quartz":256,"minecraft:stone_stairs":1928,"minecraft:spruce_stairs":2772,"minecraft:polished_diorite":4984,"minecraft:stripped_birch_wood":24,"minecraft:red_shulker_box":24,"minecraft:stone_pickaxe":21,"minecraft:quartz_slab":4896,"minecraft:chainmail_leggings":28,"minecraft:light_gray_terracotta":72,"minecraft:light_blue_glazed_terracotta":24,"minecraft:acacia_trapdoor":682,"minecraft:light_blue_wool":1,"minecraft:enchanted_book":438,"minecraft:orange_dye":516,"minecraft:magenta_glazed_terracotta":24,"minecraft:red_stained_glass":2152,"minecraft:chainmail_boots":59,"minecraft:fermented_spider_eye":64,"minecraft:black_glazed_terracotta":24,"minecraft:writable_book":25,"minecraft:note_block":120,"minecraft:pink_terracotta":60,"minecraft:cobblestone_slab":738,"minecraft:barrel":240,"minecraft:quartz_bricks":4,"minecraft:stone":510,"minecraft:heavy_weighted_pressure_plate":3,"minecraft:quartz_pillar":72,"minecraft:cake":59,"minecraft:stone_brick_slab":2128,"minecraft:bow":1,"minecraft:comparator":138,"minecraft:chest":2625,"minecraft:yellow_terracotta":60,"minecraft:birch_button":1,"minecraft:ender_eye":2,"minecraft:stone_bricks":14168,"minecraft:oak_fence":249,"minecraft:respawn_anchor":1,"minecraft:polished_diorite_slab":1182,"minecraft:granite_stairs":512,"minecraft:sea_lantern":608,"minecraft:dropper":63,"minecraft:lime_terracotta":72,"minecraft:iron_helmet":59,"minecraft:chainmail_chestplate":43,"minecraft:acacia_button":66,"minecraft:dispenser":20,"minecraft:green_glazed_terracotta":48,"minecraft:tnt":134,"minecraft:spruce_trapdoor":1232,"minecraft:yellow_dye":1972,"minecraft:purple_dye":128,"minecraft:gray_terracotta":12,"minecraft:stick":6735,"minecraft:iron_ingot":54239,"minecraft:light_blue_shulker_box":1,"minecraft:polished_diorite_stairs":2196,"minecraft:blue_terracotta":36,"minecraft:stone_brick_wall":600,"minecraft:spruce_button":42,"minecraft:mossy_stone_bricks":255,"minecraft:furnace":65,"minecraft:piston":1193,"minecraft:oak_trapdoor":1256,"minecraft:flint_and_steel":24,"minecraft:scaffolding":1626,"minecraft:granite_wall":768,"minecraft:polished_granite_stairs":2268,"minecraft:orange_terracotta":48,"minecraft:cobblestone_wall":1366,"minecraft:honey_block":333,"minecraft:birch_sign":48,"minecraft:magma_cream":12,"minecraft:smooth_sandstone_stairs":4,"minecraft:purple_terracotta":48,"minecraft:stripped_spruce_wood":33,"minecraft:iron_trapdoor":548,"minecraft:diorite_wall":2304,"minecraft:acacia_boat":9,"minecraft:jungle_planks":352,"minecraft:white_dye":19081,"minecraft:anvil":4,"minecraft:diorite_slab":1082,"minecraft:torch":748,"minecraft:granite_slab":512,"minecraft:ender_chest":2,"minecraft:smooth_stone":1,"minecraft:oak_pressure_plate":1,"minecraft:birch_slab":2674,"minecraft:slime_block":11641,"minecraft:lever":537,"minecraft:bookshelf":38,"minecraft:dark_prismarine_stairs":484,"minecraft:quartz_block":376,"minecraft:light_blue_terracotta":48,"minecraft:repeater":259,"minecraft:diamond_leggings":3,"minecraft:melon_seeds":28,"minecraft:birch_fence_gate":368,"minecraft:magenta_dye":483,"minecraft:target":119,"minecraft:emerald":20469,"minecraft:cooked_porkchop":4,"minecraft:diamond_axe":10,"minecraft:oak_wood":138,"minecraft:hay_block":299,"minecraft:green_terracotta":48,"minecraft:iron_block":54542,"minecraft:white_terracotta":168,"minecraft:gold_ingot":14558,"minecraft:light_gray_dye":1728,"minecraft:elytra":11,"minecraft:fire_charge":192,"minecraft:birch_stairs":228,"minecraft:stone_shovel":73,"minecraft:smooth_stone_slab":4706,"minecraft:red_terracotta":36,"minecraft:bone_meal":20207,"minecraft:pink_dye":18596,"minecraft:dark_oak_fence":3,"minecraft:spruce_slab":2694,"minecraft:diamond_boots":13,"minecraft:redstone_block":1552,"minecraft:dark_oak_planks":540,"minecraft:coal_block":2323,"minecraft:firework_star":1748,"minecraft:cyan_glazed_terracotta":120,"minecraft:crossbow":10,"minecraft:netherite_pickaxe":1,"minecraft:polished_granite":3536,"minecraft:snowball":4,"minecraft:glowstone":213,"minecraft:white_stained_glass":47928,"minecraft:golden_apple":10,"minecraft:acacia_sign":18,"minecraft:oak_stairs":536,"minecraft:iron_leggings":29,"minecraft:white_bed":460,"minecraft:lime_wool":1,"minecraft:brick":110,"minecraft:oak_planks":11098,"minecraft:pink_shulker_box":1,"minecraft:cobblestone_stairs":712,"minecraft:green_dye":209,"minecraft:hopper":698,"minecraft:honey_bottle":28,"minecraft:iron_boots":60,"minecraft:chiseled_stone_bricks":397,"minecraft:stone_hoe":54,"minecraft:golden_sword":9,"minecraft:quartz_stairs":296,"minecraft:item_frame":10,"minecraft:oak_slab":2476,"minecraft:acacia_wood":204,"minecraft:crafting_table":25,"minecraft:spruce_planks":15271,"minecraft:baked_potato":11,"minecraft:gold_block":1659,"minecraft:hopper_minecart":40,"minecraft:birch_planks":15836,"minecraft:black_shulker_box":28,"minecraft:dark_oak_slab":492,"minecraft:paper":12192,"minecraft:diamond_pickaxe":122,"minecraft:emerald_block":512,"minecraft:shield":81,"minecraft:birch_fence":48,"minecraft:light_blue_dye":96,"minecraft:redstone_torch":1582,"minecraft:sponge":124,"minecraft:shears":8,"minecraft:polished_andesite":2756,"minecraft:gray_glazed_terracotta":108,"minecraft:redstone":5589,"minecraft:stone_button":717,"minecraft:gray_dye":1712,"minecraft:dark_oak_sign":6,"minecraft:enchanted_golden_apple":7,"minecraft:glass_pane":960,"minecraft:end_stone_bricks":16,"minecraft:black_terracotta":96,"minecraft:iron_axe":2,"minecraft:spruce_wood":48,"minecraft:slime_ball":219,"minecraft:lime_dye":2702,"minecraft:filled_map":2,"minecraft:netherite_scrap":28,"minecraft:minecart":91,"minecraft:blue_glazed_terracotta":72,"minecraft:observer":382,"minecraft:red_dye":14807,"minecraft:cyan_dye":398,"minecraft:spruce_sign":6,"minecraft:nether_bricks":1587,"minecraft:bucket":5275,"minecraft:stone_axe":91,"minecraft:brown_terracotta":84,"minecraft:lodestone":1,"minecraft:air":0,"minecraft:bread":158,"minecraft:blue_dye":281,"minecraft:black_stained_glass":92296,"minecraft:oak_boat":1,"minecraft:magenta_terracotta":60,"minecraft:smooth_sandstone_slab":12,"minecraft:white_wool":272,"minecraft:gold_nugget":704,"minecraft:dark_prismarine_slab":282,"minecraft:acacia_planks":29232,"minecraft:end_crystal":5,"minecraft:clay":64,"minecraft:firework_rocket":42927},"minecraft:custom":{"minecraft:interact_with_crafting_table":3383,"minecraft:damage_blocked_by_shield":3170,"minecraft:deaths":82,"minecraft:jump":201532,"minecraft:inspect_dispenser":602,"minecraft:horse_one_cm":80820,"minecraft:inspect_dropper":533,"minecraft:interact_with_anvil":2304,"minecraft:inspect_hopper":3373,"minecraft:tune_noteblock":774,"minecraft:time_since_rest":108720,"minecraft:swim_one_cm":279348,"minecraft:open_chest":18278,"minecraft:open_shulker_box":72639,"minecraft:damage_resisted":17927,"minecraft:play_noteblock":42,"minecraft:talked_to_villager":4617,"minecraft:interact_with_brewingstand":301,"minecraft:interact_with_beacon":495,"minecraft:fill_cauldron":1,"minecraft:raid_win":5,"minecraft:boat_one_cm":66986,"minecraft:damage_taken":218274,"minecraft:aviate_one_cm":548777907,"minecraft:open_barrel":1501,"minecraft:eat_cake_slice":31,"minecraft:leave_game":1333,"minecraft:time_since_death":2169684,"minecraft:interact_with_furnace":1552,"minecraft:traded_with_villager":22985,"minecraft:sleep_in_bed":685,"minecraft:damage_dealt":353045,"minecraft:interact_with_smithing_table":33,"minecraft:sneak_time":923001,"minecraft:interact_with_lectern":2,"minecraft:interact_with_blast_furnace":15,"minecraft:interact_with_stonecutter":6,"minecraft:fly_one_cm":85584552,"minecraft:fall_one_cm":5969843,"minecraft:animals_bred":88,"minecraft:sprint_one_cm":139580662,"minecraft:drop":63415,"minecraft:walk_on_water_one_cm":3256473,"minecraft:play_one_minute":36336382,"minecraft:interact_with_loom":1,"minecraft:open_enderchest":567,"minecraft:player_kills":24,"minecraft:crouch_one_cm":2444010,"minecraft:mob_kills":332792,"minecraft:climb_one_cm":589534,"minecraft:walk_one_cm":86624810,"minecraft:walk_under_water_one_cm":3844577,"minecraft:raid_trigger":2,"minecraft:damage_absorbed":1077,"minecraft:trigger_trapped_chest":762,"minecraft:minecart_one_cm":648486},"minecraft:used":{"minecraft:writable_book":24,"minecraft:jack_o_lantern":57,"minecraft:smooth_quartz_slab":2063,"minecraft:dispenser":63,"minecraft:stone":17141,"minecraft:quartz_stairs":348,"minecraft:warped_sign":4,"minecraft:rotten_flesh":90,"minecraft:soul_sand":175,"minecraft:snowball":38,"minecraft:packed_ice":3043,"minecraft:lava_bucket":5152,"minecraft:quartz_pillar":6,"minecraft:villager_spawn_egg":3,"minecraft:red_wool":1,"minecraft:quartz_block":2546,"minecraft:dark_oak_leaves":1,"minecraft:dark_oak_slab":406,"minecraft:diorite_wall":4,"minecraft:bow":1302,"minecraft:cooked_cod":472,"minecraft:oak_sapling":850,"minecraft:acacia_fence":9,"minecraft:end_stone_brick_stairs":19,"minecraft:dark_prismarine_stairs":650,"minecraft:mossy_stone_bricks":557,"minecraft:damaged_anvil":3,"minecraft:chorus_fruit":85,"minecraft:prismarine":2,"minecraft:cactus":36,"minecraft:composter":505,"minecraft:clay":1,"minecraft:golden_apple":1,"minecraft:cut_sandstone_slab":1,"minecraft:blast_furnace":58,"minecraft:acacia_leaves":10,"minecraft:chiseled_quartz_block":21,"minecraft:gray_concrete":1511,"minecraft:purple_concrete_powder":11,"minecraft:birch_fence":36,"minecraft:red_sandstone":1,"minecraft:birch_slab":1357,"minecraft:oak_pressure_plate":2,"minecraft:diamond_sword":1717,"minecraft:coal_block":1,"minecraft:smithing_table":19,"minecraft:poisonous_potato":1,"minecraft:oak_boat":1,"minecraft:birch_log":2006,"minecraft:oak_trapdoor":2326,"minecraft:armor_stand":2,"minecraft:cooked_salmon":2594,"minecraft:torch":826,"minecraft:brewing_stand":2,"minecraft:nether_quartz_ore":3,"minecraft:oak_fence_gate":96,"minecraft:sea_lantern":649,"minecraft:chipped_anvil":6,"minecraft:iron_block":8430,"minecraft:jungle_log":42,"minecraft:barrel":216,"minecraft:basalt":20,"minecraft:podzol":87,"minecraft:acacia_planks":6484,"minecraft:horn_coral_fan":1,"minecraft:wheat_seeds":1495,"minecraft:light_blue_shulker_box":85,"minecraft:birch_planks":10429,"minecraft:blue_concrete_powder":18792,"minecraft:cauldron":7,"minecraft:spruce_fence_gate":2,"minecraft:gold_ore":3,"minecraft:diamond_block":5,"minecraft:rail":762,"minecraft:red_bed":43,"minecraft:white_bed":473,"minecraft:campfire":111,"minecraft:spruce_log":1021,"minecraft:diamond_pickaxe":1715941,"minecraft:acacia_sign":16,"minecraft:diamond_shovel":44864,"minecraft:suspicious_stew":6,"minecraft:magenta_concrete_powder":7,"minecraft:spruce_sapling":247,"minecraft:spruce_trapdoor":1100,"minecraft:green_carpet":8,"minecraft:potion":127,"minecraft:orange_banner":1,"minecraft:cooked_porkchop":766,"minecraft:stripped_oak_log":353,"minecraft:dandelion":1,"minecraft:green_stained_glass":1,"minecraft:red_sand":126,"minecraft:nether_wart":48,"minecraft:grass":3,"minecraft:spruce_leaves":398,"minecraft:orange_glazed_terracotta":9,"minecraft:obsidian":46074,"minecraft:bricks":17,"minecraft:spruce_wood":12,"minecraft:lantern":40,"minecraft:item_frame":17,"minecraft:birch_button":1,"minecraft:golden_sword":43,"minecraft:blue_shulker_box":104,"minecraft:gold_block":42,"minecraft:pink_concrete_powder":18,"minecraft:end_rod":5,"minecraft:dropper":140,"minecraft:wither_skeleton_skull":1,"minecraft:stripped_acacia_log":9,"minecraft:oak_planks":199,"minecraft:polished_diorite_slab":3,"minecraft:sandstone":248,"minecraft:sugar_cane":2,"minecraft:diamond_axe":1190,"minecraft:white_wool":41,"minecraft:light_blue_concrete":365,"minecraft:light_blue_wool":1,"minecraft:yellow_concrete":21,"minecraft:crossbow":6,"minecraft:end_stone":34,"minecraft:sticky_piston":447,"minecraft:lever":144,"minecraft:daylight_detector":38,"minecraft:dark_oak_log":49,"minecraft:bread":62,"minecraft:brown_wool":15,"minecraft:iron_door":3,"minecraft:light_blue_concrete_powder":1021,"minecraft:smooth_stone_slab":4015,"minecraft:coarse_dirt":41,"minecraft:bone_meal":1726,"minecraft:orange_concrete_powder":1,"minecraft:netherite_sword":2009,"minecraft:flint_and_steel":1252,"minecraft:redstone":2624,"minecraft:ender_chest":8,"minecraft:stripped_birch_wood":22,"minecraft:dirt":15641,"minecraft:prismarine_bricks":283,"minecraft:spruce_fence":1056,"minecraft:light_gray_stained_glass":1,"minecraft:oak_stairs":351,"minecraft:smooth_sandstone":243,"minecraft:yellow_concrete_powder":2764,"minecraft:black_stained_glass":62686,"minecraft:soul_soil":59,"minecraft:dark_oak_pressure_plate":18,"minecraft:netherite_pickaxe":316797,"minecraft:minecart":243,"minecraft:cyan_concrete_powder":34090,"minecraft:cooked_beef":143,"minecraft:enchanted_golden_apple":37,"minecraft:pumpkin":201,"minecraft:turtle_egg":16,"minecraft:quartz_bricks":1,"minecraft:cobblestone_stairs":240,"minecraft:lodestone":2,"minecraft:baked_potato":1215,"minecraft:birch_boat":3,"minecraft:cut_sandstone":6,"minecraft:spruce_sign":36,"minecraft:dark_prismarine_slab":244,"minecraft:red_mushroom":1,"minecraft:netherite_block":2,"minecraft:piston":3569,"minecraft:gray_terracotta":24,"minecraft:lapis_ore":1,"minecraft:detector_rail":25,"minecraft:magenta_concrete":1,"minecraft:yellow_wool":1,"minecraft:magenta_banner":1,"minecraft:pink_shulker_box":31,"minecraft:lapis_block":1,"minecraft:pumpkin_pie":41,"minecraft:sea_pickle":29,"minecraft:gray_wool":19,"minecraft:birch_stairs":20,"minecraft:peony":2,"minecraft:nether_brick_fence":1,"minecraft:dead_horn_coral_block":1,"minecraft:spruce_slab":1794,"minecraft:ladder":14,"minecraft:chest":1325,"minecraft:brown_concrete":77,"minecraft:white_shulker_box":655,"minecraft:acacia_button":1,"minecraft:acacia_sapling":15,"minecraft:blue_stained_glass":1,"minecraft:allium":1,"minecraft:stripped_spruce_log":303,"minecraft:honey_block":17,"minecraft:netherite_shovel":96145,"minecraft:grass_block":3404,"minecraft:birch_sapling":2,"minecraft:polished_andesite_stairs":6,"minecraft:orange_shulker_box":29,"minecraft:pink_wool":1,"minecraft:stone_brick_stairs":992,"minecraft:rabbit_stew":1,"minecraft:dark_oak_boat":1,"minecraft:furnace":56,"minecraft:egg":71,"minecraft:potato":1036,"minecraft:dragon_head":5,"minecraft:brown_concrete_powder":69,"minecraft:magenta_shulker_box":8,"minecraft:emerald_ore":1,"minecraft:diorite":700,"minecraft:end_stone_bricks":52,"minecraft:stripped_birch_log":2249,"minecraft:red_stained_glass":308,"minecraft:acacia_trapdoor":28,"minecraft:powered_rail":611,"minecraft:lime_concrete_powder":1,"minecraft:oak_leaves":88,"minecraft:smooth_quartz_stairs":1,"minecraft:cookie":14,"minecraft:respawn_anchor":1,"minecraft:dark_oak_trapdoor":1,"minecraft:sand":41772,"minecraft:smooth_red_sandstone":1,"minecraft:blue_ice":4,"minecraft:black_concrete_powder":1923,"minecraft:stone_button":59,"minecraft:lectern":476,"minecraft:red_terracotta":1,"minecraft:polished_granite":1,"minecraft:diamond_ore":1,"minecraft:lilac":1,"minecraft:polished_andesite_slab":1,"minecraft:pufferfish":1,"minecraft:dark_oak_fence":4,"minecraft:white_stained_glass":26025,"minecraft:green_concrete_powder":1,"minecraft:pink_stained_glass":91589,"minecraft:ice":1321,"minecraft:gray_stained_glass":28,"minecraft:iron_bars":4,"minecraft:acacia_log":7,"minecraft:red_concrete":40,"minecraft:mycelium":1,"minecraft:netherrack":30424,"minecraft:light_gray_shulker_box":15,"minecraft:anvil":51,"minecraft:target":192,"minecraft:stone_stairs":15,"minecraft:nether_brick_slab":1,"minecraft:blue_concrete":33,"minecraft:polished_diorite":197,"minecraft:shroomlight":6,"minecraft:red_shulker_box":92,"minecraft:iron_axe":20,"minecraft:brick_stairs":2,"minecraft:slime_block":338,"minecraft:smooth_quartz":2,"minecraft:totem_of_undying":24,"minecraft:tripwire_hook":20,"minecraft:glowstone":410,"minecraft:tall_grass":2,"minecraft:iron_trapdoor":125,"minecraft:observer":1879,"minecraft:orange_terracotta":25,"minecraft:water_bucket":2364,"minecraft:yellow_banner":1,"minecraft:yellow_shulker_box":11,"minecraft:smooth_sandstone_slab":11,"minecraft:lime_wool":1,"minecraft:fletching_table":66,"minecraft:polished_blackstone_bricks":11,"minecraft:cracked_stone_bricks":746,"minecraft:salmon":6,"minecraft:pink_concrete":319,"minecraft:mossy_cobblestone":96,"minecraft:comparator":600,"minecraft:vine":3,"minecraft:tnt":952,"minecraft:oak_slab":1865,"minecraft:crafting_table":32,"minecraft:birch_sign":50,"minecraft:lime_shulker_box":8,"minecraft:cake":32,"minecraft:oak_log":855,"minecraft:dark_prismarine":1397,"minecraft:ghast_spawn_egg":23,"minecraft:stripped_jungle_log":81,"minecraft:sunflower":1,"minecraft:crimson_nylium":1,"minecraft:chiseled_stone_bricks":176,"minecraft:cobblestone":3266,"minecraft:red_concrete_powder":94,"minecraft:glass_pane":47,"minecraft:diamond_hoe":5,"minecraft:oak_sign":13,"minecraft:white_concrete_powder":154,"minecraft:shield":82,"minecraft:white_terracotta":41,"minecraft:player_head":18,"minecraft:smooth_sandstone_stairs":14,"minecraft:nether_bricks":10021,"minecraft:prismarine_brick_stairs":60,"minecraft:carrot":79,"minecraft:milk_bucket":1,"minecraft:glass":2520,"minecraft:cyan_terracotta":11,"minecraft:coal_ore":31,"minecraft:quartz_slab":5281,"minecraft:gray_concrete_powder":51,"minecraft:hopper_minecart":51,"minecraft:stone_bricks":10952,"minecraft:bedrock":1,"minecraft:repeater":751,"minecraft:redstone_lamp":35,"minecraft:magma_block":50,"minecraft:hay_block":68,"minecraft:scaffolding":1028,"minecraft:beetroot_seeds":1169,"minecraft:fire_coral_fan":11,"minecraft:stripped_spruce_wood":39,"minecraft:dark_oak_stairs":1,"minecraft:birch_leaves":52,"minecraft:dark_oak_sign":7,"minecraft:ender_pearl":6,"minecraft:redstone_block":160,"minecraft:black_banner":2,"minecraft:light_gray_terracotta":36,"minecraft:sponge":1173,"minecraft:note_block":138,"minecraft:stone_brick_wall":143,"minecraft:shears":425,"minecraft:redstone_torch":688,"minecraft:green_concrete":1,"minecraft:firework_rocket":1149,"minecraft:birch_fence_gate":354,"minecraft:heavy_weighted_pressure_plate":6,"minecraft:light_gray_concrete":538,"minecraft:melon_slice":4,"minecraft:string":15,"minecraft:gravel":305,"minecraft:stripped_oak_wood":9,"minecraft:grindstone":6,"minecraft:andesite":1191,"minecraft:white_concrete":2101,"minecraft:experience_bottle":2,"minecraft:oak_fence":304,"minecraft:jungle_leaves":1,"minecraft:redstone_ore":5,"minecraft:light_blue_terracotta":14,"minecraft:spruce_planks":635,"minecraft:end_stone_brick_wall":2,"minecraft:white_carpet":730,"minecraft:hopper":1014,"minecraft:spruce_stairs":2398,"minecraft:cobblestone_wall":585,"minecraft:shulker_box":2601,"minecraft:oak_wood":91,"minecraft:pink_carpet":3,"minecraft:granite":425,"minecraft:light_blue_stained_glass":104,"minecraft:purple_banner":1,"minecraft:stone_brick_slab":570,"minecraft:dark_oak_planks":3,"minecraft:bookshelf":43,"minecraft:yellow_stained_glass":3,"minecraft:light_gray_wool":2076,"minecraft:emerald_block":2,"minecraft:stone_pressure_plate":342,"minecraft:cooked_mutton":27,"minecraft:acacia_boat":4,"minecraft:iron_ore":2,"minecraft:glass_bottle":93,"minecraft:polished_andesite":99,"minecraft:pink_banner":1,"minecraft:andesite_slab":1,"minecraft:black_shulker_box":360,"minecraft:magenta_stained_glass":21,"minecraft:stonecutter":11,"minecraft:beacon":118,"minecraft:cobblestone_slab":10,"minecraft:stripped_dark_oak_log":1,"minecraft:terracotta":112,"minecraft:light_gray_concrete_powder":3951,"minecraft:smoker":2,"minecraft:nether_gold_ore":1,"minecraft:purple_stained_glass":1,"minecraft:activator_rail":9,"minecraft:apple":64,"minecraft:cracked_polished_blackstone_bricks":11,"minecraft:map":5,"minecraft:netherite_axe":11038,"minecraft:acacia_fence_gate":50,"minecraft:green_shulker_box":28,"minecraft:white_banner":2,"minecraft:bucket":14770,"minecraft:smooth_stone":18788,"minecraft:splash_potion":105},"minecraft:killed_by":{"minecraft:zombie_villager":1,"minecraft:zombie":4,"minecraft:zombified_piglin":2,"minecraft:drowned":1,"minecraft:skeleton":1,"minecraft:vindicator":7,"minecraft:slime":4,"minecraft:creeper":6,"minecraft:piglin":1,"minecraft:player":1,"minecraft:enderman":4,"minecraft:iron_golem":1,"minecraft:phantom":1},"minecraft:picked_up":{"minecraft:suspicious_stew":2,"minecraft:smithing_table":26,"minecraft:lead":20,"minecraft:stone_slab":129,"minecraft:enchanted_book":42,"minecraft:blue_concrete":155,"minecraft:music_disc_cat":1,"minecraft:string":419,"minecraft:dark_oak_pressure_plate":32,"minecraft:orange_glazed_terracotta":55,"minecraft:shroomlight":16,"minecraft:diamond_leggings":36,"minecraft:hopper_minecart":1,"minecraft:diamond_ore":31,"minecraft:acacia_log":3735,"minecraft:purpur_pillar":11,"minecraft:end_crystal":2,"minecraft:cauldron":28,"minecraft:green_terracotta":12,"minecraft:golden_chestplate":7,"minecraft:pink_terracotta":12,"minecraft:stone_sword":17,"minecraft:lime_carpet":4,"minecraft:blue_glazed_terracotta":49,"minecraft:polished_basalt":63,"minecraft:carved_pumpkin":188,"minecraft:glowstone":190,"minecraft:bookshelf":18,"minecraft:end_rod":15,"minecraft:white_terracotta":176,"minecraft:blaze_rod":56,"minecraft:iron_bars":95,"minecraft:snowball":27,"minecraft:sponge":303,"minecraft:feather":22,"minecraft:cooked_beef":62,"minecraft:water_bucket":35,"minecraft:flint":569,"minecraft:pink_concrete_powder":894,"minecraft:cyan_concrete_powder":1784,"minecraft:magenta_terracotta":12,"minecraft:lantern":63,"minecraft:gray_concrete_powder":275,"minecraft:purple_carpet":5,"minecraft:stonecutter":12,"minecraft:dark_oak_sign":6,"minecraft:diamond_helmet":35,"minecraft:honeycomb":3,"minecraft:chiseled_polished_blackstone":16,"minecraft:lime_terracotta":12,"minecraft:birch_fence_gate":39,"minecraft:stripped_spruce_log":303,"minecraft:dead_fire_coral_fan":2,"minecraft:netherite_block":1,"minecraft:polished_andesite":3,"minecraft:lever":572,"minecraft:granite":84579,"minecraft:spruce_button":1,"minecraft:jack_o_lantern":2,"minecraft:crimson_roots":7,"minecraft:diamond_pickaxe":148,"minecraft:bee_nest":1,"minecraft:clay_ball":336,"minecraft:leather_leggings":5,"minecraft:redstone_lamp":22,"minecraft:dragon_head":7,"minecraft:acacia_button":1,"minecraft:heavy_weighted_pressure_plate":6,"minecraft:cornflower":70,"minecraft:elytra":98,"minecraft:acacia_door":2,"minecraft:flint_and_steel":12,"minecraft:white_carpet":34134,"minecraft:white_stained_glass":1857,"minecraft:iron_shovel":2,"minecraft:glass_pane":34,"minecraft:netherite_sword":21,"minecraft:poppy":8356,"minecraft:spruce_slab":123,"minecraft:minecart":224,"minecraft:birch_sapling":506,"minecraft:piston":2179,"minecraft:diamond_hoe":2,"minecraft:lime_shulker_box":8,"minecraft:black_stained_glass":800,"minecraft:stone":483903,"minecraft:cyan_glazed_terracotta":46,"minecraft:fire_charge":1,"minecraft:white_dye":683,"minecraft:netherite_pickaxe":45,"minecraft:stone_shovel":12,"minecraft:diamond_chestplate":8,"minecraft:hay_block":4,"minecraft:yellow_terracotta":12,"minecraft:totem_of_undying":18,"minecraft:mutton":9,"minecraft:rail":1100,"minecraft:bone_block":99,"minecraft:emerald_ore":3,"minecraft:oxeye_daisy":278,"minecraft:birch_leaves":6,"minecraft:yellow_shulker_box":12,"minecraft:clock":1,"minecraft:tripwire_hook":42,"minecraft:red_glazed_terracotta":14,"minecraft:yellow_dye":2,"minecraft:blackstone_slab":1,"minecraft:lily_pad":282,"minecraft:paper":626,"minecraft:apple":399,"minecraft:oak_fence_gate":104,"minecraft:stone_pickaxe":1,"minecraft:iron_ore":13058,"minecraft:dark_oak_stairs":4,"minecraft:polished_andesite_stairs":214,"minecraft:milk_bucket":140,"minecraft:light_gray_stained_glass":1,"minecraft:sweet_berries":52,"minecraft:green_glazed_terracotta":12,"minecraft:lime_concrete":5,"minecraft:light_blue_stained_glass":91,"minecraft:crying_obsidian":9,"minecraft:dragon_egg":1,"minecraft:leather_helmet":5,"minecraft:diamond_shovel":43,"minecraft:coal_ore":8545,"minecraft:slime_ball":183,"minecraft:painting":1,"minecraft:birch_sign":9,"minecraft:baked_potato":1117,"minecraft:smooth_quartz_slab":5,"minecraft:hopper":809,"minecraft:light_blue_concrete":77,"minecraft:ender_chest":2,"minecraft:nether_brick_fence":342,"minecraft:gilded_blackstone":18,"minecraft:stone_brick_stairs":380,"minecraft:lapis_block":63,"minecraft:red_sand":4,"minecraft:smooth_stone":22761,"minecraft:comparator":113,"minecraft:bucket":122,"minecraft:red_dye":467,"minecraft:rose_bush":9,"minecraft:cobblestone_slab":256,"minecraft:smooth_quartz":14,"minecraft:smooth_quartz_stairs":3,"minecraft:acacia_fence":1,"minecraft:spruce_stairs":53,"minecraft:netherite_shovel":16,"minecraft:diorite":81675,"minecraft:vine":211,"minecraft:rotten_flesh":2017,"minecraft:music_disc_ward":1,"minecraft:chorus_flower":20,"minecraft:obsidian":15654,"minecraft:cobblestone":712177,"minecraft:leather_chestplate":1,"minecraft:lilac":248,"minecraft:repeater":323,"minecraft:andesite":84454,"minecraft:orange_carpet":2167,"minecraft:black_bed":1,"minecraft:golden_leggings":23,"minecraft:beacon":37,"minecraft:potato":899,"minecraft:smooth_sandstone_stairs":12,"minecraft:prismarine_bricks":968,"minecraft:dirt":68795,"minecraft:stripped_birch_log":1974,"minecraft:name_tag":70,"minecraft:glass":5193,"minecraft:bone":2079,"minecraft:acacia_planks":1652,"minecraft:bow":38,"minecraft:wheat_seeds":782,"minecraft:grindstone":2,"minecraft:popped_chorus_fruit":30,"minecraft:netherite_axe":26,"minecraft:mossy_stone_bricks":292,"minecraft:fletching_table":77,"minecraft:cyan_concrete":8,"minecraft:prismarine":233,"minecraft:diorite_wall":4,"minecraft:gray_stained_glass":3,"minecraft:light_blue_shulker_box":92,"minecraft:melon":3,"minecraft:nether_brick_stairs":39,"minecraft:grass_block":11513,"minecraft:diamond_block":1,"minecraft:spectral_arrow":10,"minecraft:mossy_cobblestone":94,"minecraft:jungle_leaves":2,"minecraft:light_gray_terracotta":2,"minecraft:sugar":179,"minecraft:light_blue_terracotta":14,"minecraft:slime_block":1452,"minecraft:netherite_helmet":11,"minecraft:cracked_polished_blackstone_bricks":49,"minecraft:bone_meal":6204,"minecraft:crossbow":30,"minecraft:grass":15,"minecraft:golden_apple":2,"minecraft:spruce_sign":28,"minecraft:emerald":1463,"minecraft:piglin_banner_pattern":2,"minecraft:netherrack":115481,"minecraft:chorus_fruit":81,"minecraft:oak_leaves":321,"minecraft:azure_bluet":7,"minecraft:ladder":5,"minecraft:brown_mushroom":159,"minecraft:packed_ice":3898,"minecraft:stone_brick_wall":51,"minecraft:diorite_slab":4,"minecraft:chain":1,"minecraft:shield":13,"minecraft:brick":60,"minecraft:oak_trapdoor":621,"minecraft:blackstone":599,"minecraft:blue_orchid":1,"minecraft:end_stone":3757,"minecraft:note_block":38,"minecraft:polished_blackstone_bricks":159,"minecraft:brown_concrete_powder":6,"minecraft:cookie":14,"minecraft:music_disc_11":1,"minecraft:trident":4,"minecraft:stone_pressure_plate":383,"minecraft:purple_terracotta":12,"minecraft:blue_concrete_powder":2815,"minecraft:red_shulker_box":100,"minecraft:pumpkin_pie":41,"minecraft:nether_bricks":22913,"minecraft:nether_brick_wall":38,"minecraft:netherite_boots":11,"minecraft:basalt":514,"minecraft:magenta_banner":1,"minecraft:leather":41,"minecraft:ice":249,"minecraft:crimson_fungus":2,"minecraft:chainmail_chestplate":3,"minecraft:cobblestone_wall":134,"minecraft:gunpowder":2135,"minecraft:orange_terracotta":21,"minecraft:cooked_mutton":22,"minecraft:red_carpet":10,"minecraft:gray_carpet":4,"minecraft:acacia_trapdoor":361,"minecraft:iron_ingot":7202,"minecraft:cooked_chicken":57,"minecraft:prismarine_brick_slab":2,"minecraft:polished_andesite_slab":3,"minecraft:warped_fungus":1,"minecraft:nether_quartz_ore":569,"minecraft:emerald_block":3,"minecraft:stone_brick_slab":175,"minecraft:quartz":3040,"minecraft:dandelion":21,"minecraft:lava_bucket":183,"minecraft:red_banner":34,"minecraft:nether_brick_slab":19,"minecraft:spruce_door":44,"minecraft:light_blue_concrete_powder":5019,"minecraft:pumpkin_seeds":216,"minecraft:white_concrete_powder":26709,"minecraft:gray_banner":1,"minecraft:chainmail_leggings":15,"minecraft:terracotta":194,"minecraft:damaged_anvil":2,"minecraft:sunflower":799,"minecraft:iron_chestplate":3,"minecraft:chainmail_boots":6,"minecraft:flower_pot":3,"minecraft:anvil":170,"minecraft:prismarine_shard":156,"minecraft:magenta_carpet":65,"minecraft:diamond_sword":17,"minecraft:oak_stairs":35,"minecraft:wither_rose":3,"minecraft:brewing_stand":13,"minecraft:golden_sword":344,"minecraft:dark_oak_trapdoor":2,"minecraft:soul_soil":1212,"minecraft:cooked_salmon":1114,"minecraft:beetroot":17,"minecraft:orange_concrete_powder":6903,"minecraft:gold_nugget":2789,"minecraft:spruce_planks":820,"minecraft:acacia_sign":1,"minecraft:acacia_fence_gate":26,"minecraft:written_book":3,"minecraft:enchanted_golden_apple":1,"minecraft:melon_slice":52,"minecraft:coal_block":7,"minecraft:dark_oak_door":3,"minecraft:golden_helmet":8,"minecraft:white_glazed_terracotta":12,"minecraft:magenta_concrete_powder":6,"minecraft:composter":360,"minecraft:pink_carpet":118,"minecraft:sandstone_wall":16,"minecraft:black_dye":1191,"minecraft:tropical_fish":59,"minecraft:blue_dye":55,"minecraft:iron_block":2453,"minecraft:cyan_terracotta":1,"minecraft:netherite_chestplate":1,"minecraft:blackstone_stairs":1,"minecraft:birch_log":683,"minecraft:magma_block":1027,"minecraft:iron_door":39,"minecraft:birch_slab":164,"minecraft:jungle_log":116,"minecraft:acacia_leaves":19,"minecraft:green_concrete_powder":8435,"minecraft:stripped_spruce_wood":8,"minecraft:netherite_leggings":2,"minecraft:gray_concrete":832,"minecraft:light_gray_concrete_powder":2260,"minecraft:chipped_anvil":30,"minecraft:glowstone_dust":213,"minecraft:gray_glazed_terracotta":61,"minecraft:dropper":94,"minecraft:ink_sac":73,"minecraft:granite_slab":4,"minecraft:loom":1,"minecraft:trapped_chest":12,"minecraft:dark_oak_log":285,"minecraft:red_terracotta":5,"minecraft:barrel":48,"minecraft:stripped_acacia_log":18,"minecraft:dispenser":20,"minecraft:black_concrete_powder":4129,"minecraft:green_concrete":2,"minecraft:writable_book":1,"minecraft:blue_ice":1,"minecraft:chainmail_helmet":5,"minecraft:bread":32,"minecraft:bricks":199,"minecraft:spruce_leaves":42,"minecraft:crafting_table":20,"minecraft:nether_wart":1923,"minecraft:red_bed":44,"minecraft:snow":68,"minecraft:compass":25,"minecraft:cracked_stone_bricks":249,"minecraft:cartography_table":8,"minecraft:respawn_anchor":1,"minecraft:beef":45,"minecraft:iron_nugget":146,"minecraft:quartz_stairs":204,"minecraft:chest":1039,"minecraft:egg":21,"minecraft:sandstone":2339,"minecraft:oak_door":2,"minecraft:spruce_fence":106,"minecraft:carrot":42,"minecraft:redstone":3903,"minecraft:prismarine_crystals":43,"minecraft:blue_carpet":2299,"minecraft:tnt":899,"minecraft:cooked_cod":27,"minecraft:beetroot_seeds":3,"minecraft:peony":993,"minecraft:shears":15,"minecraft:diamond_boots":33,"minecraft:warped_sign":1,"minecraft:tube_coral_block":1,"minecraft:gold_ingot":214,"minecraft:white_shulker_box":743,"minecraft:lime_concrete_powder":10648,"minecraft:white_wool":1807,"minecraft:lapis_ore":53,"minecraft:stripped_oak_log":461,"minecraft:red_mushroom":265,"minecraft:filled_map":19,"minecraft:brown_concrete":64,"minecraft:oak_log":610,"minecraft:ancient_debris":63,"minecraft:golden_boots":14,"minecraft:white_banner":104,"minecraft:stone_bricks":4779,"minecraft:kelp":156,"minecraft:glass_bottle":220,"minecraft:iron_sword":3,"minecraft:prismarine_brick_stairs":21,"minecraft:dark_oak_slab":19,"minecraft:daylight_detector":4,"minecraft:yellow_concrete":222,"minecraft:gravel":29115,"minecraft:birch_stairs":74,"minecraft:spruce_sapling":791,"minecraft:spruce_log":1865,"minecraft:sea_lantern":74,"minecraft:firework_rocket":7946,"minecraft:red_stained_glass":5,"minecraft:stone_axe":9,"minecraft:light_blue_carpet":13,"minecraft:redstone_ore":166,"minecraft:diamond_axe":24,"minecraft:gray_wool":14,"minecraft:warped_roots":1,"minecraft:stripped_dark_oak_log":40,"minecraft:crimson_nylium":25,"minecraft:pink_dye":577,"minecraft:ender_pearl":73,"minecraft:shulker_shell":2644,"minecraft:wheat":156,"minecraft:redstone_block":251,"minecraft:iron_trapdoor":93,"minecraft:light_gray_shulker_box":14,"minecraft:turtle_egg":18,"minecraft:potion":50,"minecraft:nether_brick":262,"minecraft:smooth_stone_slab":1707,"minecraft:iron_leggings":1,"minecraft:ghast_spawn_egg":2,"minecraft:armor_stand":24,"minecraft:sticky_piston":330,"minecraft:netherite_ingot":3,"minecraft:pink_shulker_box":30,"minecraft:oak_sign":17,"minecraft:sea_pickle":39,"minecraft:activator_rail":51,"minecraft:black_shulker_box":356,"minecraft:dark_oak_leaves":9,"minecraft:redstone_torch":227,"minecraft:iron_boots":49,"minecraft:furnace":150,"minecraft:stick":4618,"minecraft:orange_shulker_box":30,"minecraft:brown_terracotta":12,"minecraft:oak_fence":240,"minecraft:torch":684,"minecraft:target":4,"minecraft:dead_brain_coral_fan":4,"minecraft:yellow_concrete_powder":8254,"minecraft:quartz_block":860,"minecraft:nether_gold_ore":148,"minecraft:cactus":5650,"minecraft:fire_coral_fan":9,"minecraft:stripped_birch_wood":9,"minecraft:cod":13,"minecraft:nautilus_shell":61,"minecraft:magma_cream":4,"minecraft:chiseled_quartz_block":21,"minecraft:light_gray_dye":138,"minecraft:wither_skeleton_skull":42,"minecraft:acacia_boat":7,"minecraft:green_shulker_box":30,"minecraft:lapis_lazuli":1067,"minecraft:polished_granite":64,"minecraft:leather_boots":6,"minecraft:pink_banner":7,"minecraft:light_blue_dye":1,"minecraft:powered_rail":1510,"minecraft:oak_planks":920,"minecraft:stone_hoe":2,"minecraft:ghast_tear":39,"minecraft:pink_stained_glass":3169,"minecraft:pink_concrete":344,"minecraft:black_terracotta":12,"minecraft:cooked_porkchop":475,"minecraft:music_disc_13":1,"minecraft:poisonous_potato":56,"minecraft:sand":61569,"minecraft:lily_of_the_valley":2,"minecraft:shulker_box":2931,"minecraft:dark_prismarine":117,"minecraft:light_gray_concrete":204,"minecraft:dark_prismarine_slab":2,"minecraft:spruce_fence_gate":56,"minecraft:clay":115,"minecraft:diamond":387,"minecraft:black_concrete":334,"minecraft:white_concrete":628,"minecraft:oak_sapling":3623,"minecraft:end_stone_bricks":1,"minecraft:fishing_rod":13,"minecraft:end_stone_brick_stairs":3,"minecraft:allium":1,"minecraft:chicken":18,"minecraft:turtle_helmet":1,"minecraft:gold_block":83,"minecraft:diamond_horse_armor":3,"minecraft:stone_stairs":343,"minecraft:iron_axe":13,"minecraft:item_frame":23,"minecraft:quartz_slab":2030,"minecraft:cyan_carpet":8,"minecraft:detector_rail":210,"minecraft:dark_prismarine_stairs":116,"minecraft:oak_boat":1,"minecraft:player_head":39,"minecraft:observer":517,"minecraft:light_gray_wool":2,"minecraft:lectern":481,"minecraft:blue_shulker_box":106,"minecraft:sugar_cane":36737,"minecraft:spruce_trapdoor":269,"minecraft:phantom_membrane":27,"minecraft:dark_oak_sapling":4,"minecraft:bowl":15,"minecraft:brown_glazed_terracotta":46,"minecraft:gray_dye":7,"minecraft:quartz_pillar":174,"minecraft:stone_button":79,"minecraft:magenta_shulker_box":7,"minecraft:dark_oak_planks":5,"minecraft:smooth_sandstone_slab":3,"minecraft:arrow":2188,"minecraft:saddle":24,"minecraft:wet_sponge":137,"minecraft:crimson_stem":7,"minecraft:salmon":119,"minecraft:cut_sandstone":6,"minecraft:birch_planks":481,"minecraft:nether_wart_block":11,"minecraft:cobblestone_stairs":49,"minecraft:podzol":79,"minecraft:smooth_sandstone":737,"minecraft:stripped_oak_wood":5,"minecraft:acacia_sapling":52,"minecraft:soul_sand":1229,"minecraft:purple_concrete":1,"minecraft:green_dye":725,"minecraft:book":255,"minecraft:scaffolding":859,"minecraft:oak_slab":167,"minecraft:red_concrete_powder":14624,"minecraft:birch_boat":2,"minecraft:pumpkin":13,"minecraft:chiseled_stone_bricks":259,"minecraft:blast_furnace":59,"minecraft:white_bed":326,"minecraft:gold_ore":222,"minecraft:dark_oak_fence_gate":4,"minecraft:spider_eye":197,"minecraft:stripped_jungle_log":57,"minecraft:music_disc_mall":1,"minecraft:lime_dye":28,"minecraft:honey_block":501,"minecraft:iron_helmet":26,"minecraft:stripped_jungle_wood":5,"minecraft:black_wool":1,"minecraft:acacia_slab":111,"minecraft:magenta_concrete":2,"minecraft:red_concrete":1613,"minecraft:coal":29842,"minecraft:purple_concrete_powder":11},"minecraft:dropped":{"minecraft:iron_sword":1,"minecraft:pink_stained_glass":886,"minecraft:porkchop":1279,"minecraft:lapis_lazuli":1257,"minecraft:chorus_fruit":246,"minecraft:glass_bottle":241,"minecraft:cyan_glazed_terracotta":151,"minecraft:diamond":534,"minecraft:crafting_table":11,"minecraft:lime_concrete_powder":1103,"minecraft:lime_stained_glass":10,"minecraft:cooked_porkchop":147,"minecraft:dark_oak_slab":362,"minecraft:warped_roots":93,"minecraft:black_bed":1,"minecraft:cracked_stone_bricks":2177,"minecraft:quartz_pillar":200,"minecraft:red_mushroom":354,"minecraft:gold_block":196,"minecraft:emerald":2611,"minecraft:gray_concrete":527,"minecraft:red_bed":1,"minecraft:birch_fence":22,"minecraft:dark_oak_fence":26,"minecraft:black_stained_glass_pane":231,"minecraft:dark_oak_trapdoor":1,"minecraft:netherite_boots":1,"minecraft:gold_nugget":1760,"minecraft:writable_book":1,"minecraft:acacia_fence_gate":202,"minecraft:sand":260710,"minecraft:fermented_spider_eye":96,"minecraft:dark_oak_planks":34,"minecraft:white_wool":620,"minecraft:birch_stairs":283,"minecraft:diorite_slab":388,"minecraft:dark_oak_door":3,"minecraft:stone_axe":76,"minecraft:compass":35,"minecraft:ancient_debris":10,"minecraft:diamond_block":19,"minecraft:lever":840,"minecraft:iron_nugget":145,"minecraft:cooked_chicken":57,"minecraft:gray_banner":1,"minecraft:wheat":1431,"minecraft:netherite_sword":6,"minecraft:obsidian":6359,"minecraft:rotten_flesh":7718,"minecraft:grindstone":41,"minecraft:oak_planks":1259,"minecraft:pink_carpet":118,"minecraft:glowstone_dust":218,"minecraft:warped_sign":1,"minecraft:quartz_bricks":3,"minecraft:nether_brick_fence":19,"minecraft:azure_bluet":7,"minecraft:dead_fire_coral_block":4,"minecraft:rabbit_foot":24,"minecraft:blue_stained_glass":13,"minecraft:sea_lantern":531,"minecraft:coal_ore":12254,"minecraft:diorite_wall":464,"minecraft:quartz_block":1831,"minecraft:jungle_log":444,"minecraft:leather_boots":6,"minecraft:acacia_sapling":25,"minecraft:leather_leggings":5,"minecraft:painting":2,"minecraft:glass":5997,"minecraft:beef":200,"minecraft:podzol":143,"minecraft:warped_wart_block":2,"minecraft:granite_wall":768,"minecraft:stone_brick_stairs":873,"minecraft:acacia_fence":23,"minecraft:dead_brain_coral_fan":4,"minecraft:cartography_table":2,"minecraft:brown_concrete":5,"minecraft:golden_boots":6,"minecraft:orange_shulker_box":1,"minecraft:black_dye":148,"minecraft:wheat_seeds":554,"minecraft:clock":2,"minecraft:smooth_quartz_stairs":67,"minecraft:netherite_chestplate":1,"minecraft:end_stone_brick_slab":106,"minecraft:book":142,"minecraft:prismarine_crystals":311,"minecraft:red_stained_glass":186,"minecraft:golden_apple":4,"minecraft:coal_block":1589,"minecraft:acacia_sign":4,"minecraft:lava_bucket":2014,"minecraft:cobweb":3,"minecraft:dark_oak_leaves":73,"minecraft:brown_concrete_powder":1623,"minecraft:gray_wool":65,"minecraft:ink_sac":65,"minecraft:lodestone":23,"minecraft:cooked_salmon":1262,"minecraft:lapis_ore":57,"minecraft:potion":34,"minecraft:stripped_birch_log":397,"minecraft:oak_stairs":28,"minecraft:green_glazed_terracotta":48,"minecraft:pumpkin":294,"minecraft:smooth_sandstone_slab":2,"minecraft:white_banner":70,"minecraft:red_dye":156,"minecraft:chipped_anvil":6,"minecraft:smooth_stone":10551,"minecraft:chainmail_leggings":43,"minecraft:smooth_sandstone":658,"minecraft:blue_carpet":192,"minecraft:trapped_chest":12,"minecraft:lily_pad":300,"minecraft:acacia_planks":1786,"minecraft:stone_brick_slab":407,"minecraft:snow_block":188,"minecraft:yellow_concrete_powder":27040,"minecraft:bricks":481,"minecraft:soul_soil":515,"minecraft:green_terracotta":48,"minecraft:light_blue_glazed_terracotta":24,"minecraft:sticky_piston":228,"minecraft:stone_shovel":64,"minecraft:red_banner":46,"minecraft:white_carpet":28290,"minecraft:clay_ball":237,"minecraft:iron_boots":96,"minecraft:damaged_anvil":1,"minecraft:name_tag":31,"minecraft:light_gray_concrete":290,"minecraft:white_terracotta":399,"minecraft:white_shulker_box":27,"minecraft:oak_sign":45,"minecraft:shears":15,"minecraft:blast_furnace":20,"minecraft:diamond_sword":2,"minecraft:brain_coral_block":1,"minecraft:flower_pot":7,"minecraft:sea_pickle":255,"minecraft:piglin_banner_pattern":2,"minecraft:peony":97,"minecraft:spruce_trapdoor":217,"minecraft:spruce_planks":784,"minecraft:diamond_pickaxe":115,"minecraft:light_blue_carpet":128,"minecraft:pink_shulker_box":2,"minecraft:fire_coral_block":7,"minecraft:popped_chorus_fruit":57,"minecraft:redstone_torch":534,"minecraft:stone_pressure_plate":1147,"minecraft:stone_bricks":11421,"minecraft:bamboo":4,"minecraft:sandstone":2405,"minecraft:bow":31,"minecraft:red_sand":20,"minecraft:stripped_spruce_wood":50,"minecraft:green_concrete_powder":1777,"minecraft:magma_block":877,"minecraft:cooked_rabbit":22,"minecraft:terracotta":356,"minecraft:nether_brick_stairs":23,"minecraft:soul_sand":925,"minecraft:orange_dye":64,"minecraft:warped_fungus":18,"minecraft:oak_log":1246,"minecraft:loom":1,"minecraft:ender_pearl":82,"minecraft:nether_star":87,"minecraft:dark_oak_sapling":4,"minecraft:tube_coral_block":11,"minecraft:lime_terracotta":72,"minecraft:leather":51,"minecraft:honeycomb":3,"minecraft:prismarine_brick_stairs":74,"minecraft:jungle_planks":189,"minecraft:mossy_cobblestone_wall":320,"minecraft:birch_slab":1353,"minecraft:cod":315,"minecraft:orange_glazed_terracotta":100,"minecraft:cobblestone_stairs":90,"minecraft:redstone_lamp":26,"minecraft:dark_oak_log":461,"minecraft:packed_ice":1002,"minecraft:ice":1645,"minecraft:mutton":2,"minecraft:snowball":31,"minecraft:prismarine_brick_slab":4,"minecraft:black_shulker_box":12,"minecraft:wet_sponge":222,"minecraft:stripped_oak_wood":18,"minecraft:black_concrete":252,"minecraft:cauldron":21,"minecraft:gold_ingot":551,"minecraft:red_glazed_terracotta":1,"minecraft:chiseled_polished_blackstone":16,"minecraft:magenta_stained_glass":1,"minecraft:pink_terracotta":48,"minecraft:purpur_block":86,"minecraft:stripped_jungle_wood":27,"minecraft:twisting_vines":10,"minecraft:smooth_sandstone_stairs":1,"minecraft:beetroot":3674,"minecraft:mossy_stone_brick_slab":23,"minecraft:cooked_mutton":15,"minecraft:birch_fence_gate":63,"minecraft:mossy_stone_brick_wall":343,"minecraft:oak_wood":6,"minecraft:dropper":97,"minecraft:horn_coral_fan":21,"minecraft:beetroot_seeds":1881,"minecraft:fire_coral_fan":90,"minecraft:stone_brick_wall":520,"minecraft:acacia_slab":155,"minecraft:purple_concrete_powder":1245,"minecraft:iron_ore":19295,"minecraft:iron_bars":214,"minecraft:white_concrete_powder":7252,"minecraft:scaffolding":604,"minecraft:light_gray_concrete_powder":9342,"minecraft:polished_granite":1796,"minecraft:splash_potion":3,"minecraft:purple_carpet":128,"minecraft:stone_hoe":55,"minecraft:bread":724,"minecraft:golden_helmet":4,"minecraft:lilac":7,"minecraft:yellow_concrete":342,"minecraft:netherite_axe":10,"minecraft:activator_rail":21,"minecraft:tropical_fish":73,"minecraft:spruce_stairs":289,"minecraft:acacia_log":3719,"minecraft:acacia_trapdoor":699,"minecraft:spruce_fence_gate":131,"minecraft:iron_block":6145,"minecraft:mossy_cobblestone_slab":36,"minecraft:milk_bucket":35,"minecraft:green_dye":1945,"minecraft:repeater":242,"minecraft:nether_wart_block":54,"minecraft:white_concrete":1864,"minecraft:melon_slice":2029,"minecraft:yellow_shulker_box":3,"minecraft:iron_door":37,"minecraft:fire_charge":25,"minecraft:jungle_leaves":2,"minecraft:polished_andesite_stairs":186,"minecraft:granite_slab":516,"minecraft:blue_glazed_terracotta":166,"minecraft:stonecutter":8,"minecraft:polished_basalt":62,"minecraft:cactus":181,"minecraft:tripwire_hook":39,"minecraft:redstone_block":454,"minecraft:polished_diorite":1857,"minecraft:blue_terracotta":96,"minecraft:sweet_berries":52,"minecraft:kelp":191,"minecraft:oak_trapdoor":696,"minecraft:dragon_head":1,"minecraft:dark_prismarine_stairs":55,"minecraft:light_gray_terracotta":222,"minecraft:gray_glazed_terracotta":150,"minecraft:comparator":163,"minecraft:stripped_oak_log":332,"minecraft:green_concrete":1,"minecraft:totem_of_undying":1,"minecraft:shulker_box":262,"minecraft:flint_and_steel":10,"minecraft:gray_terracotta":4,"minecraft:andesite":92647,"minecraft:golden_leggings":14,"minecraft:oak_sapling":1759,"minecraft:birch_sign":21,"minecraft:brain_coral":1,"minecraft:gray_concrete_powder":761,"minecraft:spruce_log":2793,"minecraft:nautilus_shell":99,"minecraft:magma_cream":131,"minecraft:light_blue_terracotta":48,"minecraft:brick":376,"minecraft:magenta_terracotta":71,"minecraft:crimson_stem":37,"minecraft:clay":240,"minecraft:acacia_wood":204,"minecraft:piston":765,"minecraft:oak_pressure_plate":1,"minecraft:cooked_beef":170,"minecraft:emerald_ore":27,"minecraft:sandstone_stairs":4,"minecraft:crossbow":11,"minecraft:fletching_table":45,"minecraft:saddle":10,"minecraft:purpur_stairs":6,"minecraft:bubble_coral_fan":83,"minecraft:elytra":24,"minecraft:rail":1052,"minecraft:leather_helmet":3,"minecraft:dragon_breath":11,"minecraft:red_carpet":7,"minecraft:item_frame":15,"minecraft:red_shulker_box":38,"minecraft:dirt":64857,"minecraft:melon":3,"minecraft:grass":18,"minecraft:stone_button":511,"minecraft:yellow_dye":830,"minecraft:chain":4,"minecraft:wooden_sword":10,"minecraft:bone_meal":1586,"minecraft:bone_block":84,"minecraft:sunflower":2,"minecraft:phantom_membrane":50,"minecraft:sugar":1341,"minecraft:iron_pickaxe":1,"minecraft:dark_oak_boat":1,"minecraft:gray_dye":1527,"minecraft:end_crystal":33,"minecraft:blue_bed":1,"minecraft:cyan_carpet":64,"minecraft:bone":1425,"minecraft:oak_door":2,"minecraft:pink_concrete":264,"minecraft:note_block":71,"minecraft:brain_coral_fan":2,"minecraft:magenta_banner":1,"minecraft:emerald_block":247,"minecraft:sugar_cane":12357,"minecraft:polished_andesite_slab":3,"minecraft:golden_chestplate":6,"minecraft:detector_rail":261,"minecraft:nether_brick":1195,"minecraft:pink_dye":1812,"minecraft:birch_sapling":132,"minecraft:enchanted_golden_apple":25,"minecraft:netherite_shovel":9,"minecraft:lime_dye":2282,"minecraft:end_stone":1724,"minecraft:blaze_powder":4,"minecraft:white_bed":203,"minecraft:dark_oak_fence_gate":8,"minecraft:salmon":9240,"minecraft:acacia_button":3,"minecraft:red_stained_glass_pane":12,"minecraft:black_glazed_terracotta":24,"minecraft:yellow_stained_glass_pane":6,"minecraft:lime_bed":1,"minecraft:heavy_weighted_pressure_plate":3,"minecraft:honey_block":532,"minecraft:hopper":588,"minecraft:ladder":4,"minecraft:spruce_slab":991,"minecraft:white_dye":2664,"minecraft:end_stone_bricks":37,"minecraft:crying_obsidian":16,"minecraft:ghast_tear":366,"minecraft:white_glazed_terracotta":48,"minecraft:lectern":27,"minecraft:dead_tube_coral_block":1,"minecraft:egg":170,"minecraft:enchanted_book":50,"minecraft:iron_ingot":6907,"minecraft:blue_stained_glass_pane":10,"minecraft:netherite_pickaxe":24,"minecraft:birch_leaves":6,"minecraft:gray_stained_glass_pane":8,"minecraft:tnt":915,"minecraft:netherite_helmet":2,"minecraft:dark_prismarine_slab":127,"minecraft:iron_helmet":78,"minecraft:purpur_slab":6,"minecraft:oak_fence":441,"minecraft:feather":73,"minecraft:yellow_terracotta":416,"minecraft:cobblestone":432959,"minecraft:purple_concrete":20,"minecraft:apple":283,"minecraft:granite":93575,"minecraft:spruce_button":356,"minecraft:stripped_jungle_log":73,"minecraft:spruce_door":44,"minecraft:chainmail_helmet":25,"minecraft:coal":29649,"minecraft:end_rod":42,"minecraft:polished_andesite":1742,"minecraft:pufferfish":100,"minecraft:oxeye_daisy":22,"minecraft:iron_trapdoor":514,"minecraft:golden_carrot":12,"minecraft:sponge":1520,"minecraft:gray_bed":1,"minecraft:rose_bush":9,"minecraft:rabbit":22,"minecraft:diamond_helmet":12,"minecraft:lime_carpet":64,"minecraft:brown_terracotta":84,"minecraft:orange_concrete_powder":436,"minecraft:heart_of_the_sea":93,"minecraft:magenta_glazed_terracotta":24,"minecraft:iron_shovel":3,"minecraft:paper":912,"minecraft:string":1556,"minecraft:gray_carpet":213,"minecraft:spruce_sapling":321,"minecraft:purpur_pillar":102,"minecraft:furnace":131,"minecraft:redstone_ore":153,"minecraft:netherite_ingot":3,"minecraft:polished_diorite_slab":384,"minecraft:stone_sword":19,"minecraft:cobblestone_wall":634,"minecraft:dark_oak_sign":10,"minecraft:smooth_stone_slab":1302,"minecraft:bowl":53,"minecraft:diamond_hoe":23,"minecraft:chicken":21,"minecraft:blue_concrete":345,"minecraft:slime_block":1443,"minecraft:stone_slab":150,"minecraft:magenta_concrete":1,"minecraft:light_blue_concrete":101,"minecraft:diamond_ore":97,"minecraft:nether_bricks":3479,"minecraft:spruce_fence":393,"minecraft:pumpkin_seeds":370,"minecraft:lily_of_the_valley":2,"minecraft:target":89,"minecraft:potato":6303,"minecraft:cobblestone_slab":200,"minecraft:hay_block":37,"minecraft:shroomlight":32,"minecraft:stone":370532,"minecraft:carved_pumpkin":30,"minecraft:spider_eye":378,"minecraft:light_gray_dye":1481,"minecraft:magenta_concrete_powder":2515,"minecraft:blue_orchid":1,"minecraft:magenta_dye":378,"minecraft:bell":1,"minecraft:dark_prismarine":450,"minecraft:cyan_concrete_powder":1344,"minecraft:pink_concrete_powder":3769,"minecraft:black_wool":1,"minecraft:quartz_slab":1267,"minecraft:crimson_nylium":8,"minecraft:gold_ore":451,"minecraft:spruce_sign":72,"minecraft:warped_stem":6,"minecraft:birch_planks":802,"minecraft:brown_mushroom":323,"minecraft:dark_oak_stairs":67,"minecraft:diamond_axe":10,"minecraft:baked_potato":723,"minecraft:lime_shulker_box":3,"minecraft:stripped_birch_wood":33,"minecraft:scute":22,"minecraft:lantern":108,"minecraft:blue_concrete_powder":3760,"minecraft:tube_coral_fan":5,"minecraft:lime_stained_glass_pane":13,"minecraft:flint":654,"minecraft:spruce_leaves":39,"minecraft:cyan_terracotta":12,"minecraft:orange_carpet":7568,"minecraft:netherite_scrap":7,"minecraft:dispenser":24,"minecraft:cornflower":52,"minecraft:crimson_roots":1,"minecraft:seagrass":2,"minecraft:cooked_cod":290,"minecraft:white_stained_glass_pane":7,"minecraft:gilded_blackstone":36,"minecraft:polished_blackstone_bricks":95,"minecraft:glistering_melon_slice":7,"minecraft:acacia_door":2,"minecraft:birch_log":865,"minecraft:black_stained_glass":664,"minecraft:armor_stand":22,"minecraft:gravel":27759,"minecraft:crimson_fungus":2,"minecraft:blackstone":407,"minecraft:diorite_stairs":256,"minecraft:black_terracotta":96,"minecraft:diamond_shovel":12,"minecraft:prismarine":856,"minecraft:stone_stairs":2167,"minecraft:honey_bottle":1,"minecraft:carrot":6750,"minecraft:chainmail_chestplate":45,"minecraft:poppy":144040,"minecraft:sandstone_wall":16,"minecraft:chiseled_stone_bricks":254,"minecraft:shulker_shell":438,"minecraft:rabbit_hide":67,"minecraft:oak_fence_gate":154,"minecraft:turtle_helmet":1,"minecraft:gunpowder":3261,"minecraft:birch_trapdoor":64,"minecraft:melon_seeds":28,"minecraft:glowstone":200,"minecraft:chainmail_boots":51,"minecraft:chest":842,"minecraft:cyan_concrete":8,"minecraft:arrow":948,"minecraft:basalt":488,"minecraft:powered_rail":1221,"minecraft:prismarine_bricks":1126,"minecraft:quartz":3000,"minecraft:written_book":21,"minecraft:oak_leaves":353,"minecraft:netherrack":63725,"minecraft:enchanting_table":2,"minecraft:firework_rocket":4661,"minecraft:water_bucket":43,"minecraft:purple_terracotta":48,"minecraft:oak_slab":690,"minecraft:stripped_spruce_log":325,"minecraft:magenta_carpet":2,"minecraft:red_concrete_powder":18500,"minecraft:chorus_flower":136,"minecraft:mossy_cobblestone":93,"minecraft:smithing_table":15,"minecraft:minecart":82,"minecraft:bookshelf":25,"minecraft:cyan_dye":256,"minecraft:diamond_leggings":6,"minecraft:poisonous_potato":149,"minecraft:prismarine_shard":21,"minecraft:lead":18,"minecraft:spectral_arrow":68,"minecraft:observer":448,"minecraft:dark_oak_pressure_plate":14,"minecraft:hopper_minecart":2,"minecraft:light_blue_concrete_powder":6246,"minecraft:nether_brick_wall":12,"minecraft:dead_horn_coral_block":2,"minecraft:grass_block":9998,"minecraft:stick":3797,"minecraft:blue_dye":99,"minecraft:diorite":95213,"minecraft:nether_gold_ore":56,"minecraft:brewing_stand":65,"minecraft:light_blue_stained_glass":29,"minecraft:torch":1091,"minecraft:smooth_quartz":36,"minecraft:brown_wool":380,"minecraft:map":34,"minecraft:iron_leggings":20,"minecraft:smooth_quartz_slab":136,"minecraft:wither_rose":66,"minecraft:iron_axe":7,"minecraft:granite_stairs":512,"minecraft:bucket":243,"minecraft:music_disc_cat":1,"minecraft:lapis_block":120,"minecraft:dandelion":24,"minecraft:redstone":5035,"minecraft:red_concrete":1345,"minecraft:nether_brick_slab":19,"minecraft:anvil":3186,"minecraft:gray_stained_glass":2,"minecraft:warped_nylium":49,"minecraft:ender_chest":3,"minecraft:nether_wart":996,"minecraft:blaze_rod":73,"minecraft:composter":137,"minecraft:brown_glazed_terracotta":46,"minecraft:wither_skeleton_skull":167,"minecraft:light_gray_wool":6,"minecraft:glass_pane":1177,"minecraft:acacia_leaves":11,"minecraft:red_terracotta":341,"minecraft:filled_map":8,"minecraft:snow":60,"minecraft:shield":83,"minecraft:black_concrete_powder":3650,"minecraft:dead_horn_coral_fan":7,"minecraft:diamond_chestplate":7,"minecraft:orange_terracotta":72,"minecraft:dragon_egg":116,"minecraft:fire_coral":2,"minecraft:mossy_stone_bricks":334,"minecraft:quartz_stairs":1169,"minecraft:purple_bed":1,"minecraft:pink_wool":62,"minecraft:blue_ice":2,"minecraft:oak_boat":1,"minecraft:golden_sword":135,"minecraft:diamond_boots":7,"minecraft:slime_ball":200,"minecraft:stripped_acacia_log":9,"minecraft:beacon":1,"minecraft:stone_pickaxe":11,"minecraft:nether_quartz_ore":351,"minecraft:dead_brain_coral_block":4,"minecraft:white_stained_glass":1770,"minecraft:light_blue_shulker_box":2},"minecraft:broken":{"minecraft:diamond_helmet":1,"minecraft:diamond_shovel":1,"minecraft:diamond_pickaxe":5,"minecraft:leather_helmet":1,"minecraft:diamond_leggings":1,"minecraft:shield":1,"minecraft:iron_boots":1,"minecraft:iron_axe":1,"minecraft:flint_and_steel":11},"minecraft:killed":{"minecraft:skeleton_horse":3,"minecraft:tropical_fish":1,"minecraft:salmon":5,"minecraft:iron_golem":50,"minecraft:pillager":134,"minecraft:zombie":795,"minecraft:evoker":12,"minecraft:vindicator":56,"minecraft:husk":6,"minecraft:ravager":13,"minecraft:zombified_piglin":1219,"minecraft:witch":40,"minecraft:spider":186,"minecraft:silverfish":167,"minecraft:piglin":27,"minecraft:zombie_villager":24,"minecraft:sheep":11,"minecraft:trader_llama":5,"minecraft:ghast":89,"minecraft:vex":8,"minecraft:slime":108,"minecraft:drowned":26,"minecraft:hoglin":2,"minecraft:squid":1,"minecraft:wither_skeleton":781,"minecraft:player":18,"minecraft:villager":13,"minecraft:cave_spider":4,"minecraft:skeleton":280,"minecraft:chicken":9,"minecraft:cat":5,"minecraft:magma_cube":30,"minecraft:cow":17,"minecraft:wandering_trader":1,"minecraft:enderman":18,"minecraft:wolf":1,"minecraft:pig":1,"minecraft:strider":1,"minecraft:creeper":51,"minecraft:stray":2,"minecraft:blaze":4,"minecraft:phantom":12,"minecraft:bat":7},"minecraft:mined":{"minecraft:dragon_wall_head":4,"minecraft:cut_sandstone_slab":4,"minecraft:red_shulker_box":95,"minecraft:blackstone_stairs":1,"minecraft:white_bed":135,"minecraft:granite":85621,"minecraft:acacia_log":71,"minecraft:green_concrete":2,"minecraft:oak_wall_sign":6,"minecraft:spawner":8,"minecraft:polished_blackstone_bricks":102,"minecraft:magma_block":1673,"minecraft:barrel":48,"minecraft:fire":195,"minecraft:fletching_table":69,"minecraft:nether_brick_stairs":17,"minecraft:light_gray_concrete":64,"minecraft:white_shulker_box":689,"minecraft:white_banner":1,"minecraft:player_head":3,"minecraft:tripwire":8,"minecraft:cut_sandstone":11,"minecraft:blue_concrete_powder":1686,"minecraft:kelp_plant":20,"minecraft:crimson_nylium":49,"minecraft:torch":674,"minecraft:note_block":30,"minecraft:melon":1,"minecraft:dead_bush":3,"minecraft:nether_brick_slab":18,"minecraft:spruce_wall_sign":16,"minecraft:smooth_quartz_slab":5,"minecraft:lime_shulker_box":8,"minecraft:sugar_cane":4,"minecraft:bricks":1,"minecraft:birch_sapling":1,"minecraft:white_terracotta":158,"minecraft:chain":3,"minecraft:repeater":93,"minecraft:infested_mossy_stone_bricks":2,"minecraft:grass":278,"minecraft:smooth_quartz":14,"minecraft:sandstone_wall":2,"minecraft:acacia_sign":2,"minecraft:dark_prismarine":41,"minecraft:brown_concrete":64,"minecraft:mossy_cobblestone":2,"minecraft:dark_oak_log":295,"minecraft:sea_lantern":59,"minecraft:end_stone":383,"minecraft:birch_fence_gate":36,"minecraft:spruce_fence":25,"minecraft:acacia_button":1,"minecraft:redstone_wire":151,"minecraft:red_mushroom":96,"minecraft:cartography_table":6,"minecraft:white_concrete_powder":125,"minecraft:redstone_ore":596,"minecraft:acacia_trapdoor":21,"minecraft:light_blue_concrete_powder":543,"minecraft:pink_concrete":22,"minecraft:andesite":89085,"minecraft:vine":273,"minecraft:respawn_anchor":1,"minecraft:cyan_concrete":9,"minecraft:rail":553,"minecraft:bone_block":1,"minecraft:ender_chest":4,"minecraft:birch_stairs":7,"minecraft:oak_slab":13,"minecraft:redstone_block":213,"minecraft:soul_sand":1094,"minecraft:glass_pane":59,"minecraft:dandelion":3,"minecraft:tall_grass":52,"minecraft:diorite":85074,"minecraft:black_stained_glass":1285,"minecraft:red_terracotta":5,"minecraft:stripped_spruce_wood":12,"minecraft:cobblestone_wall":35,"minecraft:dark_oak_wall_sign":5,"minecraft:pink_wall_banner":7,"minecraft:purple_concrete":1,"minecraft:dark_prismarine_slab":2,"minecraft:sunflower":1,"minecraft:gravel":28695,"minecraft:cobweb":57,"minecraft:birch_sign":5,"minecraft:stone_bricks":1663,"minecraft:gold_ore":155,"minecraft:chipped_anvil":52,"minecraft:iron_trapdoor":57,"minecraft:fern":10,"minecraft:stone_pressure_plate":2,"minecraft:oak_sapling":2,"minecraft:farmland":4,"minecraft:end_stone_brick_wall":1,"minecraft:brewing_stand":14,"minecraft:spruce_trapdoor":103,"minecraft:cracked_polished_blackstone_bricks":55,"minecraft:white_concrete":319,"minecraft:composter":373,"minecraft:turtle_egg":30,"minecraft:dragon_head":3,"minecraft:iron_bars":54,"minecraft:spruce_slab":81,"minecraft:netherite_block":1,"minecraft:quartz_block":480,"minecraft:orange_terracotta":13,"minecraft:light_gray_terracotta":2,"minecraft:beacon":31,"minecraft:nether_quartz_ore":3015,"minecraft:oak_planks":116,"minecraft:wall_torch":28,"minecraft:cauldron":2,"minecraft:light_blue_terracotta":14,"minecraft:stone_stairs":1,"minecraft:warped_nylium":4,"minecraft:blue_terracotta":1,"minecraft:powered_rail":293,"minecraft:dark_oak_slab":2,"minecraft:tnt":145,"minecraft:blue_ice":2,"minecraft:smooth_stone_slab":355,"minecraft:oak_log":383,"minecraft:dirt":60806,"minecraft:pink_banner":1,"minecraft:dispenser":21,"minecraft:ancient_debris":63,"minecraft:daylight_detector":4,"minecraft:crying_obsidian":2,"minecraft:quartz_stairs":65,"minecraft:dark_oak_leaves":10,"minecraft:red_stained_glass":8,"minecraft:gray_glazed_terracotta":38,"minecraft:lever":12,"minecraft:stone_button":7,"minecraft:birch_slab":33,"minecraft:spruce_leaves":100,"minecraft:dead_horn_coral_wall_fan":3,"minecraft:crimson_stem":1,"minecraft:heavy_weighted_pressure_plate":5,"minecraft:polished_basalt":3,"minecraft:light_gray_shulker_box":14,"minecraft:detector_rail":30,"minecraft:peony":2,"minecraft:gold_block":15,"minecraft:nether_brick_fence":335,"minecraft:bookshelf":43,"minecraft:shroomlight":8,"minecraft:stripped_oak_log":456,"minecraft:wet_sponge":156,"minecraft:blue_glazed_terracotta":33,"minecraft:orange_glazed_terracotta":61,"minecraft:acacia_leaves":25,"minecraft:scaffolding":235,"minecraft:basalt":254,"minecraft:stripped_dark_oak_log":39,"minecraft:oak_fence":68,"minecraft:honey_block":65,"minecraft:gray_stained_glass":3,"minecraft:quartz_bricks":2,"minecraft:red_glazed_terracotta":36,"minecraft:red_concrete":38,"minecraft:prismarine_bricks":514,"minecraft:birch_planks":187,"minecraft:end_stone_brick_stairs":3,"minecraft:sea_pickle":15,"minecraft:ice":2892,"minecraft:white_wall_banner":13,"minecraft:bee_nest":1,"minecraft:grass_path":33,"minecraft:dead_brain_coral_wall_fan":3,"minecraft:yellow_concrete":7,"minecraft:cracked_stone_bricks":165,"minecraft:mossy_stone_bricks":196,"minecraft:dark_oak_planks":4,"minecraft:dark_prismarine_stairs":128,"minecraft:light_blue_concrete":17,"minecraft:obsidian":7869,"minecraft:carved_pumpkin":132,"minecraft:red_sand":4,"minecraft:stone_brick_wall":4,"minecraft:jungle_log":5,"minecraft:pink_stained_glass":763,"minecraft:coal_block":1,"minecraft:oxeye_daisy":1,"minecraft:hopper":559,"minecraft:crimson_fungus":2,"minecraft:chiseled_stone_bricks":72,"minecraft:light_blue_stained_glass":102,"minecraft:weeping_vines_plant":1,"minecraft:tall_seagrass":31,"minecraft:sticky_piston":258,"minecraft:dead_fire_coral_wall_fan":11,"minecraft:pumpkin":2,"minecraft:oak_sign":6,"minecraft:oak_stairs":42,"minecraft:quartz_slab":1120,"minecraft:smooth_sandstone_stairs":11,"minecraft:iron_block":1434,"minecraft:piston_head":45,"minecraft:brown_mushroom":82,"minecraft:red_bed":39,"minecraft:player_wall_head":5,"minecraft:soul_fire":5,"minecraft:cyan_glazed_terracotta":8,"minecraft:blast_furnace":59,"minecraft:dead_brain_coral_fan":3,"minecraft:glass":963,"minecraft:damaged_anvil":17,"minecraft:smooth_sandstone_slab":2,"minecraft:spruce_sign":5,"minecraft:black_concrete_powder":425,"minecraft:light_gray_stained_glass":2,"minecraft:wheat":4,"minecraft:lilac":1,"minecraft:black_bed":1,"minecraft:warped_fungus":1,"minecraft:stone_brick_stairs":132,"minecraft:prismarine_brick_stairs":20,"minecraft:oak_fence_gate":29,"minecraft:purple_concrete_powder":7,"minecraft:loom":1,"minecraft:stripped_birch_wood":9,"minecraft:blue_shulker_box":104,"minecraft:stonecutter":7,"minecraft:piston":1666,"minecraft:pink_shulker_box":30,"minecraft:dead_bubble_coral":1,"minecraft:stripped_birch_log":1810,"minecraft:jack_o_lantern":3,"minecraft:shulker_box":2688,"minecraft:nether_bricks":18276,"minecraft:allium":1,"minecraft:crimson_roots":1,"minecraft:orange_shulker_box":27,"minecraft:magenta_concrete":2,"minecraft:yellow_concrete_powder":635,"minecraft:kelp":13,"minecraft:snow":78,"minecraft:diamond_block":1,"minecraft:warped_wall_sign":1,"minecraft:magenta_concrete_powder":1,"minecraft:smooth_quartz_stairs":3,"minecraft:white_wool":1,"minecraft:smithing_table":21,"minecraft:gray_concrete":104,"minecraft:comparator":40,"minecraft:stone_brick_slab":34,"minecraft:pink_concrete_powder":35,"minecraft:observer":450,"minecraft:smooth_sandstone":83,"minecraft:light_gray_concrete_powder":339,"minecraft:emerald_ore":8,"minecraft:cyan_concrete_powder":1844,"minecraft:sponge":67,"minecraft:dropper":32,"minecraft:prismarine_brick_slab":1,"minecraft:white_carpet":53,"minecraft:spruce_log":506,"minecraft:birch_leaves":7,"minecraft:quartz_pillar":6,"minecraft:acacia_planks":113,"minecraft:spruce_fence_gate":67,"minecraft:infested_stone":204,"minecraft:black_shulker_box":348,"minecraft:spruce_planks":147,"minecraft:cobblestone_stairs":36,"minecraft:grass_block":20393,"minecraft:blue_concrete":68,"minecraft:soul_soil":1559,"minecraft:smooth_stone":2399,"minecraft:glowstone":106,"minecraft:iron_ore":13529,"minecraft:target":4,"minecraft:potted_red_mushroom":1,"minecraft:anvil":174,"minecraft:azure_bluet":2,"minecraft:dark_oak_stairs":2,"minecraft:birch_wall_sign":5,"minecraft:end_stone_bricks":3,"minecraft:blackstone":575,"minecraft:cyan_terracotta":1,"minecraft:chiseled_quartz_block":21,"minecraft:clay":63,"minecraft:poppy":3,"minecraft:chest":812,"minecraft:cobblestone":3270,"minecraft:slime_block":1292,"minecraft:grindstone":2,"minecraft:prismarine":7,"minecraft:iron_door":8,"minecraft:magenta_shulker_box":8,"minecraft:seagrass":20,"minecraft:brown_concrete_powder":5,"minecraft:nether_wart_block":2,"minecraft:lapis_block":1,"minecraft:birch_log":67,"minecraft:activator_rail":6,"minecraft:stripped_oak_wood":5,"minecraft:diorite_wall":4,"minecraft:acacia_fence":1,"minecraft:sand":21797,"minecraft:infested_cracked_stone_bricks":1,"minecraft:tripwire_hook":12,"minecraft:wither_skeleton_skull":1,"minecraft:netherrack":228850,"minecraft:oak_leaves":360,"minecraft:emerald_block":3,"minecraft:redstone_lamp":2,"minecraft:nether_gold_ore":416,"minecraft:diamond_ore":137,"minecraft:oak_door":1,"minecraft:dark_oak_pressure_plate":17,"minecraft:white_stained_glass":1168,"minecraft:sandstone":3112,"minecraft:large_fern":27,"minecraft:oak_trapdoor":286,"minecraft:furnace":157,"minecraft:red_concrete_powder":18,"minecraft:stripped_spruce_log":309,"minecraft:black_concrete":3,"minecraft:lantern":1,"minecraft:packed_ice":4260,"minecraft:stripped_acacia_log":18,"minecraft:stripped_jungle_log":57,"minecraft:stone":1435002,"minecraft:yellow_shulker_box":12,"minecraft:redstone_wall_torch":7,"minecraft:podzol":62,"minecraft:light_blue_shulker_box":86,"minecraft:infested_stone_bricks":26,"minecraft:crafting_table":23,"minecraft:blackstone_slab":1,"minecraft:lectern":468,"minecraft:lapis_ore":71,"minecraft:lily_pad":17,"minecraft:spruce_stairs":54,"minecraft:gray_concrete_powder":220,"minecraft:green_shulker_box":27,"minecraft:acacia_fence_gate":13,"minecraft:redstone_torch":109,"minecraft:sweet_berry_bush":6,"minecraft:coal_ore":22741,"minecraft:gray_carpet":2,"minecraft:terracotta":196,"minecraft:polished_andesite":3}},"DataVersion":2584}